{"hash":"cd8d0aac0213f0ac972ed2d8f2128d4ca20f1d57","data":{"tag":{"title":"Programming","belongsTo":{"edges":[{"node":{"title":"Programming skills","path":"/programming-skills/","date":"17. July 2020","timeToRead":1,"description":"プログラミングスキルのこと","content":"<p>プログラミングの経験のはなし</p>\n<h3 id=\"業務経験のある言語\"><a href=\"#%E6%A5%AD%E5%8B%99%E7%B5%8C%E9%A8%93%E3%81%AE%E3%81%82%E3%82%8B%E8%A8%80%E8%AA%9E\" aria-hidden=\"true\"><span class=\"icon icon-link\"></span></a>業務経験のある言語</h3>\n<ul>\n<li>JavaScript, Java, Python, C#, Ruby</li>\n</ul>\n<h3 id=\"業務経験はないけどほんのり程度触れる言語\"><a href=\"#%E6%A5%AD%E5%8B%99%E7%B5%8C%E9%A8%93%E3%81%AF%E3%81%AA%E3%81%84%E3%81%91%E3%81%A9%E3%81%BB%E3%82%93%E3%81%AE%E3%82%8A%E7%A8%8B%E5%BA%A6%E8%A7%A6%E3%82%8C%E3%82%8B%E8%A8%80%E8%AA%9E\" aria-hidden=\"true\"><span class=\"icon icon-link\"></span></a>業務経験はないけどほんのり程度触れる言語</h3>\n<ul>\n<li>Rust, Erlang, Elixir</li>\n</ul>\n<h3 id=\"経歴的ななにか\"><a href=\"#%E7%B5%8C%E6%AD%B4%E7%9A%84%E3%81%AA%E3%81%AA%E3%81%AB%E3%81%8B\" aria-hidden=\"true\"><span class=\"icon icon-link\"></span></a>経歴的ななにか</h3>\n<p>小学校高学年のとき、兄が親にねだって買ってもらったPC98で、兄が持ってきたフロッピーディスクに入ったプログラミングソフトと、プログラミングの雑誌を見ながらやったN88BASICが最初のプログラミング経験です。\n兄は別の道へ進んだのですが、私はコンピュータの内部動作や、プログラミングの楽しさがとてもとても気になってしまい、気づいたらプログラマになっていました。</p>\n<p>まだ書くよ</p>\n"}}]}}},"context":{}}